gimme_iphotos/__init__.py
gimme_iphotos/downloader.py
gimme_iphotos/utils.py
gimme_iphotos-1.1.3.dist-info/entry_points.txt
gimme_iphotos-1.1.3.dist-info/LICENSE
gimme_iphotos-1.1.3.dist-info/WHEEL
gimme_iphotos-1.1.3.dist-info/METADATA
gimme_iphotos-1.1.3.dist-info/RECORD
