Metadata-Version: 2.1
Name: gimme-iphotos
Version: 1.1.3
Summary: Download photos and videos from iCloud
Home-page: https://github.com/Zebradil/Gimme-iPhotos
License: MIT
Author: German Lashevich
Author-email: german.lashevich@gmail.com
Requires-Python: >=3.6,<4.0
Classifier: License :: OSI Approved :: MIT License
Classifier: Programming Language :: Python :: 3
Classifier: Programming Language :: Python :: 3.10
Classifier: Programming Language :: Python :: 3.6
Classifier: Programming Language :: Python :: 3.7
Classifier: Programming Language :: Python :: 3.8
Classifier: Programming Language :: Python :: 3.9
Requires-Dist: colorama (>=0.4.3,<0.5.0)
Requires-Dist: pyicloud (>=0.10.2,<0.11.0)
Requires-Dist: tqdm (>=4.45.0,<5.0.0)
Project-URL: Repository, https://github.com/Zebradil/Gimme-iPhotos
